abm_shape_collection/__init__.py
abm_shape_collection/__main__.py
abm_shape_collection/calculate_feature_statistics.py
abm_shape_collection/calculate_shape_statistics.py
abm_shape_collection/construct_mesh_from_array.py
abm_shape_collection/construct_mesh_from_coeffs.py
abm_shape_collection/construct_mesh_from_points.py
abm_shape_collection/extract_mesh_projections.py
abm_shape_collection/extract_mesh_wireframe.py
abm_shape_collection/extract_shape_modes.py
abm_shape_collection/extract_voxel_contours.py
abm_shape_collection/fit_pca_model.py
abm_shape_collection/get_shape_coefficients.py
abm_shape_collection/get_shape_properties.py
abm_shape_collection/make_voxels_array.py
abm_shape_collection/py.typed
abm_shape_collection-0.10.0.dist-info/LICENSE
abm_shape_collection-0.10.0.dist-info/METADATA
abm_shape_collection-0.10.0.dist-info/WHEEL
abm_shape_collection-0.10.0.dist-info/RECORD
